cdp_monitoring/__init__.py
cdp_monitoring/monitoring_metrics.py
cdp_monitoring/monitoring_middleware.py
cdp_monitoring/monitoring_utils.py
cdp_monitoring-0.2.0.dist-info/METADATA
cdp_monitoring-0.2.0.dist-info/WHEEL
cdp_monitoring-0.2.0.dist-info/RECORD
